README.txt
setup.cfg
setup.py
collective/__init__.py
collective.contentrules.runscript.egg-info/PKG-INFO
collective.contentrules.runscript.egg-info/SOURCES.txt
collective.contentrules.runscript.egg-info/dependency_links.txt
collective.contentrules.runscript.egg-info/entry_points.txt
collective.contentrules.runscript.egg-info/namespace_packages.txt
collective.contentrules.runscript.egg-info/not-zip-safe
collective.contentrules.runscript.egg-info/requires.txt
collective.contentrules.runscript.egg-info/top_level.txt
collective/contentrules/__init__.py
collective/contentrules/runscript/__init__.py
collective/contentrules/runscript/configure.zcml
collective/contentrules/runscript/profiles.zcml
collective/contentrules/runscript/skins.zcml
collective/contentrules/runscript/tests.py
collective/contentrules/runscript/version.txt
collective/contentrules/runscript/actions/__init__.py
collective/contentrules/runscript/actions/configure.zcml
collective/contentrules/runscript/actions/interfaces.py
collective/contentrules/runscript/actions/runscript.py
collective/contentrules/runscript/locales/pt_BR/LC_MESSAGES/collective.contentrules.runscript.po
collective/contentrules/runscript/profiles/default/metadata.xml
collective/contentrules/runscript/profiles/default/skins.xml
collective/contentrules/runscript/skins/collective_contentrules_runscript_scripts/set_property.py
collective/contentrules/runscript/skins/collective_contentrules_runscript_scripts/set_property.py.metadata
collective/contentrules/runscript/skins/collective_contentrules_runscript_scripts/tag_after_parent.py
collective/contentrules/runscript/skins/collective_contentrules_runscript_scripts/tag_after_parent.py.metadata
collective/contentrules/runscript/skins/collective_contentrules_runscript_scripts/tag_after_parents.py
collective/contentrules/runscript/skins/collective_contentrules_runscript_scripts/tag_after_parents.py.metadata
docs/HISTORY.txt
docs/INSTALL.txt
docs/LICENSE.txt