Metadata-Version: 1.0
Name: collective.contentrules.runscript
Version: 0.4
Summary: An action for the contentrules framework to run a script on the object that triggered the rule
Home-page: http://plone.org/products/collective.contentrules.runscript
Author: Danilo G. Botelho
Author-email: danilogbotelho@yahoo.com
License: GPL
Keywords: plone contentrules action addon
Platform: UNKNOWN
Classifier: Framework :: Plone
Classifier: Programming Language :: Python
Classifier: Topic :: Software Development :: Libraries :: Python Modules
